{"name": "National Fraud Authority", "children": [{"FTE": 1.0, "name": "Chief Executive ", "children": [{"ref": "1NFA01", "FTE": 1.0, "name": "Director Interventions"}, {"ref": "1NFA02", "FTE": 1.0, "name": "Director Knowledge  ", "children": [{"FTE": 1.0, "name": "Project Manager", "junior": true}, {"FTE": 1.0, "name": "Programme Manager", "junior": true}, {"FTE": 1.0, "name": "Programme Manager", "junior": true}, {"FTE": 1.0, "name": "Project Manager", "junior": true}, {"FTE": 1.0, "name": "Project Manager", "junior": true}, {"FTE": 1.0, "name": "Project Manager", "junior": true}, {"FTE": 1.0, "name": "Project Manager", "junior": true}, {"FTE": 1.0, "name": "Project Manager", "junior": true}, {"FTE": 1.0, "name": "Project Manager", "junior": true}, {"FTE": 1.0, "name": "Project Manager", "junior": true}, {"FTE": 1.0, "name": "Project Manager", "junior": true}, {"FTE": 1.0, "name": "Project Manager", "junior": true}, {"FTE": 1.0, "name": "Project Manager", "junior": true}, {"FTE": 1.0, "name": "Project Manager", "junior": true}, {"FTE": 1.0, "name": "Project Manager", "junior": true}, {"FTE": 1.0, "name": "Project Manager", "junior": true}, {"FTE": 1.0, "name": "Project Manager", "junior": true}, {"FTE": 1.0, "name": "Project Manager", "junior": true}, {"FTE": 1.0, "name": "Project Support Officer", "junior": true}, {"FTE": 1.0, "name": "Project Support Officer", "junior": true}, {"FTE": 1.0, "name": "Project Support Officer", "junior": true}, {"FTE": 1.0, "name": "Project Manager", "junior": true}]}, {"ref": "1NFA03", "FTE": 1.0, "name": "Director Engagement", "children": [{"FTE": 1.0, "name": "Project Manager", "junior": true}, {"FTE": 1.0, "name": "Project Manager", "junior": true}, {"FTE": 1.0, "name": "Project Manager", "junior": true}, {"FTE": 1.0, "name": "Project Manager", "junior": true}, {"FTE": 1.0, "name": "Project Manager", "junior": true}, {"FTE": 1.0, "name": "Project Manager", "junior": true}, {"FTE": 1.0, "name": "Project Manager", "junior": true}, {"FTE": 1.0, "name": "Project Manager", "junior": true}, {"FTE": 1.0, "name": "Project Manager", "junior": true}, {"FTE": 1.0, "name": "Project Manager", "junior": true}, {"FTE": 1.0, "name": "Project Support Officer", "junior": true}, {"FTE": 1.0, "name": "Project Support Officer", "junior": true}, {"FTE": 1.0, "name": "Project Support Officer", "junior": true}, {"FTE": 1.0, "name": "Project Support Officer", "junior": true}, {"FTE": 1.0, "name": "Project Support Officer", "junior": true}, {"FTE": 1.0, "name": "Project Support Officer", "junior": true}, {"FTE": 1.0, "name": "Project Support Officer", "junior": true}, {"FTE": 1.0, "name": "Project Support Officer", "junior": true}, {"FTE": 1.0, "name": "Project Support Officer", "junior": true}]}, {"FTE": 1.0, "name": "Programme Officer Manager", "junior": true}, {"FTE": 1.0, "name": "Programme Manager", "junior": true}, {"FTE": 1.0, "name": "Programme Manager", "junior": true}, {"FTE": 0.6, "name": "Head of Human Resources", "junior": true}, {"FTE": 1.0, "name": "Project Manager", "junior": true}, {"FTE": 1.0, "name": "Finance Manager", "junior": true}, {"FTE": 1.0, "name": "Executive Assistant", "junior": true}, {"FTE": 1.0, "name": "Project Manager", "junior": true}, {"FTE": 1.0, "name": "Facilities Delivery Manager", "junior": true}, {"FTE": 1.0, "name": "Project Support Officer", "junior": true}, {"FTE": 1.0, "name": "Corporate Support", "junior": true}, {"FTE": 1.0, "name": "Corporate Support", "junior": true}]}]}