[{"children": [{"ref": "RPSCS008", "FTE": 1.0, "children": [{"FTE": 3.79, "junior": true, "job title": "IT & Finance Assistant "}, {"FTE": 4.79, "junior": true, "job title": "BI & eEnablement Assistant"}, {"FTE": 6.0, "junior": true, "job title": "IT & Finance Executive "}, {"FTE": 1.0, "junior": true, "job title": "Assurance Executive"}, {"FTE": 6.0, "junior": true, "job title": "BI & eEnablement Executive"}, {"FTE": 4.94, "junior": true, "job title": "IT, Finance & Programme Specialist"}, {"FTE": 4.0, "junior": true, "job title": "BI & eEnablement Specialist"}, {"FTE": 4.0, "junior": true, "job title": "Seniort IT & Finance Specialist"}, {"FTE": 4.0, "junior": true, "job title": "Audit Manager Internal and Supplier Audit"}, {"FTE": 13.0, "junior": true, "job title": "Senior BI & eEnablement Specialist"}, {"FTE": 4.0, "junior": true, "job title": "Senior IT & Finance Manager"}, {"FTE": 5.89, "junior": true, "job title": "Spend Analysis and Engagement Lead"}, {"FTE": 3.0, "junior": true, "job title": "Senior IT, Finance & Programme Lead"}, {"FTE": 1.0, "junior": true, "job title": "Senior BI & eEnablement Lead"}, {"FTE": 1.0, "junior": true, "job title": "Head of eProcurement"}], "job title": "Director of Resources"}, {"ref": "RPSCS006", "FTE": 1.0, "children": [{"FTE": 6.0, "junior": true, "job title": "Customer Service Assistant"}, {"FTE": 1.0, "junior": true, "job title": "Customer Service Executive"}, {"FTE": 5.0, "junior": true, "job title": "Customer Research Specialist"}, {"FTE": 6.0, "junior": true, "job title": "Customer & Research Manager"}, {"FTE": 5.0, "junior": true, "job title": "Customer Lead"}, {"FTE": 8.0, "junior": true, "job title": "Senior Customer & Relationship Lead"}, {"FTE": 2.0, "junior": true, "job title": "Senior Customer & Relationship Lead"}], "job title": "Director of Customer Services"}, {"ref": "RPSCS004", "FTE": 1.0, "children": [{"FTE": 1.0, "junior": true, "job title": "Sourcing Assistant"}, {"FTE": 4.29, "junior": true, "job title": "Sourcing Executive"}, {"FTE": 7.0, "junior": true, "job title": "Sourcing Specialist"}, {"FTE": 14.49, "junior": true, "job title": "Sourcing Manager"}, {"FTE": 6.48, "junior": true, "job title": "Sourcing Lead"}, {"FTE": 3.58, "junior": true, "job title": "Senior Category Lead Sourcing "}, {"FTE": 1.0, "junior": true, "job title": "Head of Sourcing Operations"}], "job title": "Director of Procurement Services"}, {"ref": "RP719", "FTE": 1.0, "children": [{"FTE": 2.0, "junior": true, "job title": "HR Assistant"}, {"FTE": 1.69, "junior": true, "job title": "HR Executive "}, {"FTE": 2.0, "junior": true, "job title": "HR Operations Manager & Training Centre Specialist"}, {"FTE": 3.83, "junior": true, "job title": "Senior HR Advisor, L&D Manager, Resourcing Manager & Training Centre Manager"}, {"FTE": 2.0, "junior": true, "job title": "Senior HR Business Partner"}, {"FTE": 1.0, "junior": true, "job title": "Head of Strategic Resourcing and Capability"}], "job title": "Director of HR"}, {"ref": "RPSCS002", "FTE": 1.0, "children": [{"FTE": 7.0, "junior": true, "job title": "Category Assistant"}, {"FTE": 21.44, "junior": true, "job title": "Category Executive"}, {"FTE": 14.0, "junior": true, "job title": "Category Specialist"}, {"FTE": 10.0, "junior": true, "job title": "Senior Category Specialist"}, {"FTE": 6.89, "junior": true, "job title": "Category Lead "}, {"FTE": 1.0, "junior": true, "job title": "Senior Category Lead"}], "job title": "Director of Sourcing & Category Management"}, {"ref": "RPSCS005", "FTE": 1.0, "children": [{"FTE": 1.0, "junior": true, "job title": "Category Assistant"}, {"FTE": 4.0, "junior": true, "job title": "Category Specialist"}, {"FTE": 4.0, "junior": true, "job title": "Senior Category Specialist"}, {"FTE": 2.0, "junior": true, "job title": "Category Lead "}, {"FTE": 2.0, "junior": true, "job title": "Senior Category Lead"}, {"FTE": 1.0, "junior": true, "job title": "Head of Sourcing and Category Management"}], "job title": "Director of Sourcing & Category Management Property"}, {"ref": "RP702", "FTE": 1.0, "children": [{"FTE": 5.53, "junior": true, "job title": "Category Executive"}, {"FTE": 7.6, "junior": true, "job title": "Category Specialist"}, {"FTE": 7.0, "junior": true, "job title": "Senior Category Specialist"}, {"FTE": 6.0, "junior": true, "job title": "Category Lead "}, {"FTE": 3.64, "junior": true, "job title": "Senior Category Lead"}], "job title": "Head of Sourcing & Category Management Energy"}, {"ref": "RP708", "FTE": 1.0, "children": [{"FTE": 19.7, "junior": true, "job title": "Category Executive"}, {"FTE": 24.5, "junior": true, "job title": "Category Specialist"}, {"FTE": 46.34, "junior": true, "job title": "Senior Category Specialist"}, {"FTE": 29.0, "junior": true, "job title": "Category Lead "}, {"FTE": 15.0, "junior": true, "job title": "Senior Category Lead"}, {"FTE": 5.0, "junior": true, "job title": "Head of Sourcing and Category Management"}], "job title": "Head of Sourcing & Category Management "}, {"FTE": 2.0, "junior": true, "job title": "Diary Secretary"}, {"FTE": 1.0, "junior": true, "job title": "FOI & Communications Executive"}, {"FTE": 1.0, "junior": true, "job title": "FOI & Communications Lead"}], "job title": "Managing Director"}]