{"jobtitle": "Wallace Collection", "children": [{"payfloor": "85000", "FTE": 1.0, "name": "Christoph Vogtherr", "grade": "SCS2", "jobtitle": "Director", "payceiling": "89999", "unit": "Director", "children": [{"payfloor": "60000", "FTE": 1.0, "name": "Jeremy Warren", "grade": "SCS1", "jobtitle": "Director of Collections & Academic", "ref": "411", "payceiling": "64999", "unit": "Collections Department", "children": [{"grade": "C", "jobtitle": "Head of Collection Services", "payceiling": "44999", "payfloor": "28500", "FTE": 1.0, "junior": true, "unit": "Collections Department"}, {"grade": "C", "jobtitle": "Senior Curator", "payceiling": "44999", "payfloor": "28500", "FTE": 1.0, "junior": true, "unit": "Collections Department"}, {"grade": "C", "jobtitle": "Head of Conservation", "payceiling": "44999", "payfloor": "28500", "FTE": 1.0, "junior": true, "unit": "Collections Department"}, {"grade": "D", "jobtitle": "Metalwork Conservation Officer", "payceiling": "38999", "payfloor": "25000", "FTE": 1.0, "junior": true, "unit": "Collections Department"}, {"grade": "D", "jobtitle": "Conservation Officer, Reynolds Project", "payceiling": "38999", "payfloor": "25000", "FTE": 0.8, "junior": true, "unit": "Collections Department"}, {"grade": "D", "jobtitle": "Librarian & Archivist", "payceiling": "38999", "payfloor": "25000", "FTE": 1.0, "junior": true, "unit": "Collections Department"}, {"grade": "D", "jobtitle": "Senior Furniture Conservator", "payceiling": "38999", "payfloor": "25000", "FTE": 1.0, "junior": true, "unit": "Collections Department"}, {"grade": "D", "jobtitle": "Curator ", "payceiling": "38999", "payfloor": "25000", "FTE": 3.69, "junior": true, "unit": "Collections Department"}, {"grade": "G", "jobtitle": "Photographer", "payceiling": "27269", "payfloor": "20535", "FTE": 1.0, "junior": true, "unit": "Collections Department"}, {"grade": "G", "jobtitle": "Curatorial Assistant", "payceiling": "27269", "payfloor": "20535", "FTE": 1.0, "junior": true, "unit": "Collections Department"}, {"grade": "G", "jobtitle": "Library Cataloguer", "payceiling": "27269", "payfloor": "20535", "FTE": 1.0, "junior": true, "unit": "Collections Department"}, {"grade": "G", "jobtitle": "Conservation Craftsman", "payceiling": "27269", "payfloor": "20535", "FTE": 1.0, "junior": true, "unit": "Collections Department"}, {"grade": "H", "jobtitle": "Project Archvist", "payceiling": "25501", "payfloor": "20535", "FTE": 1.0, "junior": true, "unit": "Collections Department"}, {"grade": "J", "jobtitle": "Research Assistant", "payceiling": "20388", "payfloor": "17852", "FTE": 1.0, "junior": true, "unit": "Collections Department"}, {"grade": "H", "jobtitle": "Picture Librarian", "payceiling": "25501", "payfloor": "20535", "FTE": 1.0, "junior": true, "unit": "Collections Department"}]}, {"payfloor": "60000", "FTE": 1.0, "name": "Clare O'Brien", "grade": "SCS1", "jobtitle": "Director of Marketing & Development", "ref": "422", "payceiling": "64999", "unit": "Development & Marketing Department", "children": [{"grade": "C", "jobtitle": "Head of Learning", "payceiling": "44999", "payfloor": "28500", "FTE": 1.0, "junior": true, "unit": "Development & Marketing Department"}, {"grade": "G", "jobtitle": "Education Officer", "payceiling": "27269", "payfloor": "20535", "FTE": 0.8, "junior": true, "unit": "Development & Marketing Department"}, {"grade": "H", "jobtitle": "Education Officer", "payceiling": "25501", "payfloor": "20535", "FTE": 1.0, "junior": true, "unit": "Development & Marketing Department"}, {"grade": "H", "jobtitle": "Education Officer", "payceiling": "25501", "payfloor": "20535", "FTE": 1.0, "junior": true, "unit": "Development & Marketing Department"}, {"grade": "J", "jobtitle": "Education Assistant", "payceiling": "20388", "payfloor": "17852", "FTE": 0.6, "junior": true, "unit": "Development & Marketing Department"}, {"grade": "C", "jobtitle": "Head of Retail & Front of House", "payceiling": "44999", "payfloor": "28500", "FTE": 1.0, "junior": true, "unit": "Development & Marketing Department"}, {"grade": "C", "jobtitle": "Head of Events", "payceiling": "44999", "payfloor": "28500", "FTE": 1.0, "junior": true, "unit": "Development & Marketing Department"}, {"grade": "F", "jobtitle": "Press & Marketing Manager", "payceiling": "31999", "payfloor": "26260", "FTE": 1.0, "junior": true, "unit": "Development & Marketing Department"}, {"grade": "G", "jobtitle": "Front of House & Retail Supervisor", "payceiling": "27269", "payfloor": "20535", "FTE": 1.0, "junior": true, "unit": "Development & Marketing Department"}, {"grade": "H", "jobtitle": "Events Officer", "payceiling": "25501", "payfloor": "20535", "FTE": 2.0, "junior": true, "unit": "Development & Marketing Department"}, {"grade": "J", "jobtitle": "Development & Marketing Assistant", "payceiling": "20388", "payfloor": "17852", "FTE": 1.0, "junior": true, "unit": "Development & Marketing Department"}, {"grade": "K", "jobtitle": "Front of House Assistant", "payceiling": "18528", "payfloor": "15715", "FTE": 9.7, "junior": true, "unit": "Development & Marketing Department"}]}, {"payfloor": "60000", "FTE": 1.0, "name": "Philip Walsh ", "grade": "SCS1", "jobtitle": "Director of Finance & Operations", "ref": "649", "payceiling": "64999", "unit": "Finance & Operations Department", "children": [{"grade": "C", "jobtitle": "Head of Security", "payceiling": "44999", "payfloor": "28500", "FTE": 1.0, "junior": true, "unit": "Finance & Operations Department"}, {"grade": "C", "jobtitle": "Head of Facilities", "payceiling": "44999", "payfloor": "28500", "FTE": 1.0, "junior": true, "unit": "Finance & Operations Department"}, {"grade": "E", "jobtitle": "Personnel Manager", "payceiling": "38999", "payfloor": "32000", "FTE": 1.0, "junior": true, "unit": "Finance & Operations Department"}, {"grade": "E", "jobtitle": "Project Manager", "payceiling": "38999", "payfloor": "32000", "FTE": 1.0, "junior": true, "unit": "Finance & Operations Department"}, {"grade": "J", "jobtitle": "Project Assistant", "payceiling": "20388", "payfloor": "17852", "FTE": 1.0, "junior": true, "unit": "Finance & Operations Department"}, {"grade": "F", "jobtitle": "Security Staff Manager", "payceiling": "31999", "payfloor": "26260", "FTE": 1.0, "junior": true, "unit": "Finance & Operations Department"}, {"grade": "F", "jobtitle": "Gallery Team Manager", "payceiling": "31999", "payfloor": "26260", "FTE": 1.0, "junior": true, "unit": "Finance & Operations Department"}, {"grade": "G", "jobtitle": "Gallery Supervisor", "payceiling": "27269", "payfloor": "20535", "FTE": 1.0, "junior": true, "unit": "Finance & Operations Department"}, {"grade": "G", "jobtitle": "Finance & Payroll Officer", "payceiling": "27269", "payfloor": "20535", "FTE": 1.0, "junior": true, "unit": "Finance & Operations Department"}, {"grade": "H", "jobtitle": "Accounts Assistant", "payceiling": "25501", "payfloor": "20535", "FTE": 1.0, "junior": true, "unit": "Finance & Operations Department"}, {"grade": "H", "jobtitle": "Facilities & IT Officer", "payceiling": "25501", "payfloor": "20535", "FTE": 0.8, "junior": true, "unit": "Finance & Operations Department"}, {"grade": "G", "jobtitle": "Security Supervisors", "payceiling": "27269", "payfloor": "20535", "FTE": 4.0, "junior": true, "unit": "Finance & Operations Department"}, {"grade": "I", "jobtitle": "Security Team Members", "payceiling": "22414", "payfloor": "18441", "FTE": 8.0, "junior": true, "unit": "Finance & Operations Department"}, {"grade": "J", "jobtitle": "HR Assistant", "payceiling": "20388", "payfloor": "17852", "FTE": 0.6, "junior": true, "unit": "Finance & Operations Department"}, {"grade": "J", "jobtitle": "Facilities Assistant", "payceiling": "20388", "payfloor": "17852", "FTE": 1.0, "junior": true, "unit": "Finance & Operations Department"}, {"grade": "K", "jobtitle": "Gallery Team Members", "payceiling": "18528", "payfloor": "15715", "FTE": 26.75, "junior": true, "unit": "Finance & Operations Department"}]}, {"grade": "F", "jobtitle": "Development Manager", "payceiling": "31999", "payfloor": "26260", "FTE": 0.4, "junior": true, "unit": "Director"}, {"grade": "H", "jobtitle": "Development Officer", "payceiling": "25501", "payfloor": "20535", "FTE": 1.0, "junior": true, "unit": "Director"}, {"grade": "G", "jobtitle": "Director's Assistant", "payceiling": "27269", "payfloor": "20535", "FTE": 1.0, "junior": true, "unit": "Director's Office"}]}]}